darth.py
darth_bootstrap.py
setup.py
darth.egg-info/PKG-INFO
darth.egg-info/SOURCES.txt
darth.egg-info/dependency_links.txt
darth.egg-info/entry_points.txt
darth.egg-info/top_level.txt