Metadata-Version: 1.1
Name: darth
Version: 0.0.6
Summary: Third-party vendoring helper for Google App Engine and other sandboxed python environments.
Home-page: https://github.com/jonparrott/Darth-Vendor
Author: Jon Wayne Parrott
Author-email: jon.wayne.parrott@gmail.com
License: Apache License 2.0
Platform: UNKNOWN
Classifier: Development Status :: 5 - Production/Stable
Classifier: License :: OSI Approved :: Apache Software License
Classifier: Programming Language :: Python
